libdl_py2f.so
dl_py2f/AUTHORS
dl_py2f/CMakeLists.txt
dl_py2f/LICENSE
dl_py2f/README.md
dl_py2f/__init__.py
dl_py2f/dl_f2py.py
dl_py2f/dl_py2f.cpp
dl_py2f/dl_py2f.f90
dl_py2f/dl_py2f.h
dl_py2f/dl_py2f.mod
dl_py2f/export.map
dl_py2f/libdir_debian.py
dl_py2f/libdl_py2f.so
dl_py2f/libpath.py
dl_py2f/libpath.py.in
dl_py2f/utils/__init__.py
dl_py2f/utils/colours.py
dl_py2f/utils/ctypeutils.py
dl_py2f/utils/dictutils.py
dl_py2f/utils/fileutils.py
dl_py2f/utils/iterutils.py
dl_py2f/utils/miscutils.py
dl_py2f/utils/modutils.py
dl_py2f/utils/nputils.py
dl_py2f/utils/objutils.py
dl_py2f/utils/strutils.py
dl_py2f-1.1.1.dist-info/METADATA
dl_py2f-1.1.1.dist-info/WHEEL
dl_py2f-1.1.1.dist-info/top_level.txt
dl_py2f-1.1.1.dist-info/RECORD
