Metadata-Version: 2.4
Name: dl_py2f
Version: 1.1.1
Summary: DL_PY2F: A library for Python-Fortran interoperability
Home-page: https://github.com/stfc/dl_py2f
Author: You Lu
Author-email: you.lu@stfc.ac.uk
License: GNU Lesser General Public License v3.0
Requires-Python: >=3.9
Requires-Dist: numpy>=1.26
Dynamic: author
Dynamic: author-email
Dynamic: home-page
Dynamic: license
Dynamic: requires-dist
Dynamic: requires-python
Dynamic: summary
